pycurses/__init__.py
pycurses/colors.py
pycurses/layout.py
pycurses/lines.py
pycurses/list_view.py
pycurses/mainwindow.py
pycurses/popup.py
pycurses/screen.py
pycurses/test_app.py
pycurses/window.py
pycurses/utils/__init__.py
pycurses/utils/general.py
pycurses/utils/input.py
pycurses/utils/keys.py
pycurses-0.0.37.dist-info/LICENSE
pycurses-0.0.37.dist-info/WHEEL
pycurses-0.0.37.dist-info/METADATA
pycurses-0.0.37.dist-info/RECORD
