Metadata-Version: 2.1
Name: pycurses
Version: 0.0.37
Summary: Python package for making terminal UIs 
Author-email: Charlie Dudzik <dudzikc@outlook.com>
Classifier: License :: OSI Approved :: MIT License
